MANIFEST.in
README.rst
setup.py
bin/pymtt
pymtt/__init__.py
pymtt.egg-info/PKG-INFO
pymtt.egg-info/SOURCES.txt
pymtt.egg-info/dependency_links.txt
pymtt.egg-info/requires.txt
pymtt.egg-info/top_level.txt
pymtt/filters/BSD.local.dist
pymtt/filters/__init__.py
pymtt/filters/plist
pymtt/filters/plist.py