Metadata-Version: 1.1
Name: pymtt
Version: 0.1.8
Summary: Command-line Text Transformer
Home-page: https://github.com/pklemenkov/pymtt
Author: Pavel Klemenkov
Author-email: pklemenkov@gmail.com
License: GPL
Download-URL: https://github.com/pklemenkov/pymtt/tarball/master
Platform: UNKNOWN
